easy/databases/__init__.py
easy_databases-0.0.0.dist-info/LICENSE
easy_databases-0.0.0.dist-info/METADATA
easy_databases-0.0.0.dist-info/WHEEL
easy_databases-0.0.0.dist-info/top_level.txt
easy_databases-0.0.0.dist-info/RECORD
