Metadata-Version: 2.1
Name: easy-databases
Version: 0.0.0
Summary: Easy-to-use pure Python databases that match basic data structures, including lists, sets, and dictionaries. No fancy querying language required.
License: mit
Project-URL: Bug Tracker, https://github.com/SimpleArt/easy-databases/issues
Project-URL: Documentation, https://simpleart.github.io/easy-databases/
Project-URL: Homepage, https://simpleart.github.io/easy-databases/
Project-URL: Repository, https://github.com/SimpleArt/easy-databases
Classifier: Operating System :: OS Independent
Classifier: Programming Language :: Python :: 3.5
Classifier: Programming Language :: Python :: 3.6
Classifier: Programming Language :: Python :: 3.7
Classifier: Programming Language :: Python :: 3.8
Classifier: Programming Language :: Python :: 3.9
Classifier: Programming Language :: Python :: 3.10
Requires-Python: >=3.7
License-File: LICENSE
